trane/__init__.py
trane/version.py
trane/core/__init__.py
trane/core/problem.py
trane/core/problem_generator.py
trane/core/utils.py
trane/datasets/__init__.py
trane/datasets/load_functions.py
trane/datasets/data/airbnb_reviews/README.md
trane/datasets/data/airbnb_reviews/airbnb_reviews.csv
trane/datasets/data/store/LICENSE
trane/datasets/data/store/README.md
trane/datasets/data/store/categories.csv
trane/datasets/data/store/cust_hist.csv
trane/datasets/data/store/customers.csv
trane/datasets/data/store/inventory.csv
trane/datasets/data/store/orderlines.csv
trane/datasets/data/store/orders.csv
trane/datasets/data/store/products.csv
trane/datasets/data/store/reorder.csv
trane/llm/__init__.py
trane/llm/helpers.py
trane/metadata/__init__.py
trane/metadata/metadata.py
trane/ops/__init__.py
trane/ops/aggregation_ops.py
trane/ops/filter_ops.py
trane/ops/op_base.py
trane/ops/threshold_functions.py
trane/ops/threshold_functions.test.py
trane/ops/transformation_ops.py
trane/ops/utils.py
trane/parsing/__init__.py
trane/parsing/denormalize.py
trane/typing/1-1000.txt
trane/typing/__init__.py
trane/typing/inference.py
trane/typing/inference_functions.py
trane/typing/ml_types.py
trane/typing/utils.py
trane/utils/__init__.py
trane/utils/library_utils.py
trane/utils/testing_utils.py
trane-0.8.0.dist-info/LICENSE
trane-0.8.0.dist-info/METADATA
trane-0.8.0.dist-info/WHEEL
trane-0.8.0.dist-info/top_level.txt
trane-0.8.0.dist-info/RECORD
