Metadata-Version: 2.1
Name: trane
Version: 0.8.0
Summary: automatically generate prediction problems and labels for supervised learning.
Author-email: MIT Data to AI Lab <dai-lab-trane@mit.edu>
Maintainer-email: MIT Data to AI Lab <dai-lab-trane@mit.edu>
License: MIT License
Project-URL: Source Code, https://github.com/trane-dev/Trane/
Project-URL: Changes, https://github.com/trane-dev/Trane/blob/main/docs/changelog.md
Project-URL: Issue Tracker, https://github.com/trane-dev/Trane/issues
Project-URL: Twitter, https://twitter.com/lab_dai
Project-URL: Chat, https://join.slack.com/t/trane-dev/shared_invite/zt-1zglnh25c-ryuQFarw0rVgKHC6ywUOlg
Keywords: trane,data science,machine learning
Classifier: Development Status :: 2 - Pre-Alpha
Classifier: Intended Audience :: Science/Research
Classifier: Intended Audience :: Developers
Classifier: Topic :: Software Development
Classifier: Topic :: Scientific/Engineering
Classifier: Programming Language :: Python
Classifier: Programming Language :: Python :: 3
Classifier: Programming Language :: Python :: 3.8
Classifier: Programming Language :: Python :: 3.9
Classifier: Programming Language :: Python :: 3.10
Classifier: Programming Language :: Python :: 3.11
Classifier: Programming Language :: Python :: 3.12
Classifier: Operating System :: Microsoft :: Windows
Classifier: Operating System :: POSIX
Classifier: Operating System :: Unix
Classifier: Operating System :: MacOS
Classifier: License :: OSI Approved :: MIT License
Classifier: Natural Language :: English
Requires-Python: <4,>=3.8
License-File: LICENSE
License-File: trane/datasets/data/store/LICENSE
Requires-Dist: numpy >=1.24.2
Requires-Dist: pandas >=2.0.1
Requires-Dist: scipy >=1.10.0
Requires-Dist: tqdm >=4.65.0
Requires-Dist: importlib-resources >=6.0.0
Requires-Dist: pyarrow >=14.0.1
Requires-Dist: humanize >=4.9.0
Provides-Extra: dev
Requires-Dist: ruff >=0.1.8 ; extra == 'dev'
Requires-Dist: pre-commit >=3.6.0 ; extra == 'dev'
Provides-Extra: llm
Requires-Dist: openai >=1.3.7 ; extra == 'llm'
Requires-Dist: anthropic >=0.7.7 ; extra == 'llm'
Requires-Dist: tiktoken >=0.5.1 ; extra == 'llm'
Provides-Extra: test
Requires-Dist: pytest >=3.4.2 ; extra == 'test'
Requires-Dist: pytest-cov >=2.5.1 ; extra == 'test'
Requires-Dist: pytest-xdist >=3.1.0 ; extra == 'test'
Requires-Dist: pytest-runner >=2.11.1 ; extra == 'test'
